{
    "_id":  "6a2d000000000000000000a1",
    "applicationId":  "69f23d0ae8d23e3922706103",
    "workspaceId":  "69f23d0ae8d23e39227060fe",
    "pluginType":  "DB",
    "pluginId":  "69f21d005fbcf7f394507fde",
    "unpublishedAction":  {
                              "name":  "productSoftDelete",
                              "datasource":  {
                                                 "_id":  "69f23e5ae8d23e3922706106",
                                                 "name":  "Supabase (dev)",
                                                 "pluginId":  "69f21d005fbcf7f394507fde",
                                                 "updatedAt":  "2026-05-12T17:25:29.697Z",
                                                 "deleted":  false,
                                                 "policyMap":  {

                                                               },
                                                 "policies":  [

                                                              ]
                                             },
                              "pageId":  "69fdcf5fc8eed02aabb4c9a5",
                              "actionConfiguration":  {
                                                          "timeoutInMillisecond":  10000,
                                                          "paginationType":  "NONE",
                                                          "encodeParamsToggle":  true,
                                                          "body":  "UPDATE public.producten\nSET deletedon = now(),\n    deletedby = \u002700000000-0000-0000-0000-000000000001\u0027::uuid\nWHERE id = \u0027{{appsmith.store.deleteProductId}}\u0027::uuid;",
                                                          "pluginSpecifiedTemplates":  [
                                                                                           {
                                                                                               "value":  true
                                                                                           }
                                                                                       ]
                                                      },
                              "executeOnLoad":  false,
                              "runBehaviour":  "MANUAL",
                              "isValid":  true,
                              "invalids":  [

                                           ],
                              "jsonPathKeys":  [
                                                   "appsmith.store.deleteProductId"
                                               ],
                              "userSetOnLoad":  false,
                              "confirmBeforeExecute":  false,
                              "createdAt":  "2026-06-13T14:20:51.000Z"
                          },
    "publishedAction":  {
                            "name":  "productSoftDelete",
                            "datasource":  {
                                               "_id":  "69f23e5ae8d23e3922706106",
                                               "name":  "Supabase (dev)",
                                               "pluginId":  "69f21d005fbcf7f394507fde",
                                               "updatedAt":  "2026-05-12T17:25:29.697Z",
                                               "deleted":  false,
                                               "policyMap":  {

                                                             },
                                               "policies":  [

                                                            ]
                                           },
                            "pageId":  "69fdcf5fc8eed02aabb4c9a5",
                            "actionConfiguration":  {
                                                        "timeoutInMillisecond":  10000,
                                                        "paginationType":  "NONE",
                                                        "encodeParamsToggle":  true,
                                                        "body":  "UPDATE public.producten\nSET deletedon = now(),\n    deletedby = \u002700000000-0000-0000-0000-000000000001\u0027::uuid\nWHERE id = \u0027{{appsmith.store.deleteProductId}}\u0027::uuid;",
                                                        "pluginSpecifiedTemplates":  [
                                                                                         {
                                                                                             "value":  true
                                                                                         }
                                                                                     ]
                                                    },
                            "executeOnLoad":  false,
                            "runBehaviour":  "MANUAL",
                            "isValid":  true,
                            "invalids":  [

                                         ],
                            "jsonPathKeys":  [
                                                 "appsmith.store.deleteProductId"
                                             ],
                            "userSetOnLoad":  false,
                            "confirmBeforeExecute":  false,
                            "createdAt":  "2026-06-13T14:20:51.000Z"
                        },
    "baseId":  "6a2d000000000000000000a1",
    "gitSyncId":  "69f23d0ae8d23e3922706103_9f1c2a3b-aaaa-bbbb-cccc-000000000a1",
    "createdAt":  "2026-06-13T14:20:51.000Z",
    "updatedAt":  "2026-06-13T14:20:51.000Z",
    "deleted":  false,
    "policyMap":  {
                      "read:actions":  {
                                           "permission":  "read:actions",
                                           "permissionGroups":  [
                                                                    "69f23d0ae8d23e39227060ff",
                                                                    "69f23d0ae8d23e3922706100"
                                                                ]
                                       },
                      "delete:actions":  {
                                             "permission":  "delete:actions",
                                             "permissionGroups":  [
                                                                      "69f23d0ae8d23e39227060ff",
                                                                      "69f23d0ae8d23e3922706100"
                                                                  ]
                                         },
                      "execute:actions":  {
                                              "permission":  "execute:actions",
                                              "permissionGroups":  [
                                                                       "69f23d0ae8d23e39227060ff",
                                                                       "69f23d0ae8d23e3922706100",
                                                                       "69f23d0ae8d23e3922706101"
                                                                   ]
                                          },
                      "manage:actions":  {
                                             "permission":  "manage:actions",
                                             "permissionGroups":  [
                                                                      "69f23d0ae8d23e39227060ff",
                                                                      "69f23d0ae8d23e3922706100"
                                                                  ]
                                         }
                  },
    "policies":  [
                     {
                         "permission":  "manage:actions",
                         "permissionGroups":  [
                                                  "69f23d0ae8d23e39227060ff",
                                                  "69f23d0ae8d23e3922706100"
                                              ]
                     },
                     {
                         "permission":  "read:actions",
                         "permissionGroups":  [
                                                  "69f23d0ae8d23e39227060ff",
                                                  "69f23d0ae8d23e3922706100"
                                              ]
                     },
                     {
                         "permission":  "delete:actions",
                         "permissionGroups":  [
                                                  "69f23d0ae8d23e39227060ff",
                                                  "69f23d0ae8d23e3922706100"
                                              ]
                     },
                     {
                         "permission":  "execute:actions",
                         "permissionGroups":  [
                                                  "69f23d0ae8d23e39227060ff",
                                                  "69f23d0ae8d23e3922706100",
                                                  "69f23d0ae8d23e3922706101"
                                              ]
                     }
                 ],
    "_class":  "com.appsmith.server.domains.NewAction"
}
